{
	"name": "wret-beacon-rebalance-mod-bobs-module-fork",
	"version": "1.0.3",
	"title": "Beacon Rebalance Bob's Module Fork",
	"author": "nattanang",
	"description": "A fork of Beacon rebalance mod that fix the compatibility of this mod & Bob's Module since the author was absent, if this mod crashed, feels free to edit this mod since this mod is using MIT license",
	"factorio_version": "2.0",
	"dependencies": [
		"base", 
		"! beacon-overhaul", 
		"! beacon-interference", 
		"! space-exploration", 
		"? FactorioExtended-Plus-Module", 
		"? Krastorio2", 
		"? PickerDollies",
		"? bobmodules",
		"? SeaBlock"
	]
}
